[ {
  "id" : "4879c187-0bbb-2afe-1a13-e3d6a3064162",
  "name" : "background_image",
  "label" : "Background Image",
  "required" : false,
  "locked" : false,
  "responsive" : true,
  "resizable" : false,
  "show_loading" : false,
  "type" : "image",
  "default" : {
    "size_type" : "auto",
    "src" : "https://f.hubspotusercontent20.net/hubfs/20618228/statics/assets/rank-mast.jpg",
    "alt" : "rank-mast",
    "loading" : "lazy",
    "width" : 1920,
    "height" : 755,
    "max_width" : 1920,
    "max_height" : 755
  }
}, {
  "id" : "a59314d9-f1bc-3ca7-d335-164de15ce369",
  "name" : "logo",
  "label" : "Logo",
  "required" : false,
  "locked" : false,
  "responsive" : true,
  "resizable" : false,
  "show_loading" : false,
  "type" : "image",
  "default" : {
    "size_type" : "auto",
    "src" : "https://f.hubspotusercontent20.net/hubfs/20618228/statics/assets/rank-logo.png",
    "alt" : "rank-logo",
    "loading" : "lazy",
    "width" : 534,
    "height" : 128,
    "max_width" : 534,
    "max_height" : 128
  }
}, {
  "id" : "f941ec92-e576-5fd7-cc73-8961d31aa69a",
  "name" : "title",
  "label" : "Title",
  "required" : false,
  "locked" : false,
  "validation_regex" : "",
  "allow_new_line" : false,
  "show_emoji_picker" : false,
  "type" : "text",
  "default" : "World-class digital academy"
}, {
  "id" : "be6e761a-c242-af7d-7564-d28644ffca82",
  "name" : "description",
  "label" : "Description",
  "required" : false,
  "locked" : false,
  "validation_regex" : "",
  "allow_new_line" : false,
  "show_emoji_picker" : false,
  "type" : "text",
  "default" : "Check in for exceptional performance training with the world's best football experts and academies. From professional drills, specialist training        for specific positions to mentoring, nutrition and rehabilitative conditioning. ZujuGP Rank is a world-class digital academy in your pocket."
}, {
  "id" : "ecef5f55-3bc6-80f6-7eae-9c7de4c08e79",
  "name" : "notify_label",
  "label" : "Notify Label",
  "required" : false,
  "locked" : false,
  "validation_regex" : "",
  "allow_new_line" : false,
  "show_emoji_picker" : false,
  "type" : "text",
  "default" : "Get Notified"
}, {
  "id" : "f100a51b-8491-cf0b-efc1-7b2d72592a47",
  "name" : "watch_video_label",
  "label" : "Watch Video Label",
  "required" : false,
  "locked" : false,
  "validation_regex" : "",
  "allow_new_line" : false,
  "show_emoji_picker" : false,
  "type" : "text",
  "default" : "Watch Video"
}, {
  "id" : "17d2a3ea-cf24-3bc2-45db-dc4e893386f4",
  "name" : "video_url",
  "label" : "Video URL",
  "required" : false,
  "locked" : false,
  "supported_types" : [ "EXTERNAL" ],
  "type" : "url",
  "default" : {
    "type" : "EXTERNAL",
    "href" : "https://f.hubspotusercontent20.net/hubfs/20618228/statics/rank.mp4",
    "content_id" : null
  }
} ]